{
    "952871361024495636": {
        "money": 5000,
        "total_games": 40,
        "wins": 36,
        "losses": 4,
        "total_bet": 1141497069,
        "total_win": 612415485,
        "winrate": 90.0,
        "created_at": "2025-10-06T16:41:55.594864",
        "last_played": "2025-10-08T06:28:40.377995",
        "games_10m_plus": 10
    },
    "1250688186422923367": {
        "money": 5000,
        "total_games": 12,
        "wins": 5,
        "losses": 7,
        "total_bet": 2050327202,
        "total_win": 327200,
        "winrate": 41.66666666666667,
        "created_at": "2025-10-06T13:06:43.696358",
        "last_played": "2025-10-11T18:17:01.856330",
        "games_10m_plus": 1
    },
    "1264908798003253314": {
        "money": 5000,
        "total_games": 34,
        "wins": 24,
        "losses": 10,
        "total_bet": 210015652,
        "total_win": 104857569,
        "winrate": 70.58823529411765,
        "created_at": "2025-10-06T13:20:20.823867",
        "last_played": "2025-10-10T01:57:08.041734"
    },
    "1389417980735262893": {
        "money": 5000,
        "total_games": 83,
        "wins": 78,
        "losses": 5,
        "total_bet": 1753060200,
        "total_win": 891329900,
        "winrate": 93.97590361445783,
        "created_at": "2025-10-06T13:43:11.442183",
        "last_played": "2025-10-08T16:42:36.604993",
        "games_10m_plus": 9
    },
    "1393166103076802592": {
        "money": 5000,
        "total_games": 0,
        "wins": 0,
        "losses": 0,
        "total_bet": 0,
        "total_win": 0,
        "winrate": 0.0,
        "created_at": "2025-10-06T13:45:38.133434",
        "last_played": "2025-10-06T13:45:38.133446"
    },
    "1308389977830326366": {
        "money": 5000,
        "total_games": 0,
        "wins": 0,
        "losses": 0,
        "total_bet": 0,
        "total_win": 0,
        "winrate": 0.0,
        "created_at": "2025-10-06T13:47:38.972576",
        "last_played": "2025-10-06T13:47:38.972586"
    },
    "1168409001034264667": {
        "money": 5000,
        "total_games": 3,
        "wins": 0,
        "losses": 3,
        "total_bet": 248374629418,
        "total_win": 0,
        "winrate": 0.0,
        "created_at": "2025-10-06T14:00:43.432227",
        "last_played": "2025-10-07T10:44:45.520560"
    },
    "1022776315457310721": {
        "money": 5000,
        "total_games": 17,
        "wins": 4,
        "losses": 13,
        "total_bet": 3078831096,
        "total_win": 163000000,
        "winrate": 23.52941176470588,
        "created_at": "2025-10-06T14:05:57.575366",
        "last_played": "2025-10-07T10:18:01.357437",
        "games_10m_plus": 11
    },
    "1212769486546018387": {
        "money": 5000,
        "total_games": 0,
        "wins": 0,
        "losses": 0,
        "total_bet": 0,
        "total_win": 0,
        "winrate": 0.0,
        "games_10m_plus": 0,
        "created_at": "2025-10-07T12:28:35.511851",
        "last_played": "2025-10-07T12:28:35.511859"
    },
    "1179187837854294056": {
        "money": 5000,
        "total_games": 11,
        "wins": 11,
        "losses": 0,
        "total_bet": 2251700,
        "total_win": 2251700,
        "winrate": 100.0,
        "games_10m_plus": 0,
        "created_at": "2025-10-08T06:29:57.575949",
        "last_played": "2025-10-08T06:47:57.271727"
    },
    "1214489739496005642": {
        "money": 5000,
        "total_games": 35,
        "wins": 32,
        "losses": 3,
        "total_bet": 79065750,
        "total_win": 78858700,
        "winrate": 91.42857142857143,
        "games_10m_plus": 2,
        "created_at": "2025-10-08T10:22:32.481066",
        "last_played": "2025-10-10T15:23:34.482466"
    },
    "1253293782590558259": {
        "money": 5000,
        "total_games": 1,
        "wins": 1,
        "losses": 0,
        "total_bet": 200,
        "total_win": 200,
        "winrate": 100.0,
        "games_10m_plus": 0,
        "created_at": "2025-10-08T16:04:09.817166",
        "last_played": "2025-10-09T04:31:37.012243"
    },
    "1270228021491798082": {
        "money": 5000,
        "total_games": 0,
        "wins": 0,
        "losses": 0,
        "total_bet": 0,
        "total_win": 0,
        "winrate": 0.0,
        "games_10m_plus": 0,
        "created_at": "2025-10-08T16:04:27.332880",
        "last_played": "2025-10-08T16:04:27.332888"
    },
    "1153280581384274000": {
        "money": 5000,
        "total_games": 0,
        "wins": 0,
        "losses": 0,
        "total_bet": 0,
        "total_win": 0,
        "winrate": 0.0,
        "games_10m_plus": 0,
        "created_at": "2025-10-08T16:04:36.110350",
        "last_played": "2025-10-08T16:04:36.110410"
    },
    "1168853555130675251": {
        "money": 5000,
        "total_games": 1,
        "wins": 1,
        "losses": 0,
        "total_bet": 1000,
        "total_win": 1000,
        "winrate": 100.0,
        "games_10m_plus": 0,
        "created_at": "2025-10-09T06:39:57.195844",
        "last_played": "2025-10-09T06:39:57.198987"
    },
    "1174471129969205414": {
        "money": 5000,
        "total_games": 1,
        "wins": 0,
        "losses": 1,
        "total_bet": 100,
        "total_win": 0,
        "winrate": 0.0,
        "games_10m_plus": 0,
        "created_at": "2025-10-10T02:02:28.758159",
        "last_played": "2025-10-10T02:02:28.761577"
    }
}